easypy/__init__.py
easypy/ovc.py
learnpyOvercompensator9000-0.0.1.dist-info/METADATA
learnpyOvercompensator9000-0.0.1.dist-info/WHEEL
learnpyOvercompensator9000-0.0.1.dist-info/top_level.txt
learnpyOvercompensator9000-0.0.1.dist-info/RECORD
