Metadata-Version: 2.1
Name: learnpyOvercompensator9000
Version: 0.0.1
Summary: Python Simplified
Home-page: UNKNOWN
Author: Overcompensator9000
Author-email: sashwathdc10z63@gmail.com
License: UNKNOWN
Platform: UNKNOWN
Classifier: Programming Language :: Python :: 3
Classifier: Operating System :: OS Independent
Requires-Python: >=3.6
